<?xml version="1.0" encoding="utf-8" ?>
<Advertisements>
  <Ad>
    <ImageUrl>http://localhost:61993/Real madrid shopping cart/Real madrid/xmlimages/14937596581988.jpg</ImageUrl>
  </Ad>
  <Ad>
    <ImageUrl>http://localhost:61993/Real madrid shopping cart/Real madrid/xmlimages/14938077538589.jpg</ImageUrl>
  </Ad>
  <Ad>
    <ImageUrl>http://localhost:61993/Real madrid shopping cart/Real madrid/xmlimages/14938398071826.jpg</ImageUrl>
  </Ad>
  <Ad>
    <ImageUrl>http://localhost:61993/Real madrid shopping cart/Real madrid/xmlimages/14938423635193.jpg</ImageUrl>
  </Ad>
  <Ad>
    <ImageUrl>http://localhost:61993/Real madrid shopping cart/Real madrid/xmlimages/14938955741386.jpg</ImageUrl>

  </Ad>
  <Ad>
    <ImageUrl>http://localhost:61993/Real madrid shopping cart/Real madrid/xmlimages/fm___real_madrid_kits_by_joaopedro16.jpg</ImageUrl>
  </Ad>
  
</Advertisements>